hydro/__init__.py
hydro/delta.py
hydro/spark.py
delta_hydro-0.4.3.dist-info/LICENSE
delta_hydro-0.4.3.dist-info/METADATA
delta_hydro-0.4.3.dist-info/WHEEL
delta_hydro-0.4.3.dist-info/top_level.txt
delta_hydro-0.4.3.dist-info/RECORD
