Metadata-Version: 2.1
Name: delta-hydro
Version: 0.4.3
Summary: Advanced Delta-Lake related tooling based on Apache Spark
Home-page: https://github.com/christophergrant/delta-hydro
Author: Christopher Grant
Author-email: backfill@protonmail.com
License: MIT
Classifier: License :: OSI Approved :: MIT License
Classifier: Programming Language :: Python :: 3
Classifier: Programming Language :: Python :: 3 :: Only
Classifier: Programming Language :: Python :: Implementation :: CPython
Classifier: Programming Language :: Python :: Implementation :: PyPy
Requires-Python: >=3.7
License-File: LICENSE
Requires-Dist: delta-spark
Requires-Dist: pyspark
